CHANGES.rst
CONTRIBUTORS.rst
MANIFEST.in
README.rst
setup.cfg
setup.py
docs/LICENSE.GPL
docs/LICENSE.rst
docs/index.rst
src/experimental/__init__.py
src/experimental.publishtraverse.egg-info/PKG-INFO
src/experimental.publishtraverse.egg-info/SOURCES.txt
src/experimental.publishtraverse.egg-info/dependency_links.txt
src/experimental.publishtraverse.egg-info/entry_points.txt
src/experimental.publishtraverse.egg-info/namespace_packages.txt
src/experimental.publishtraverse.egg-info/not-zip-safe
src/experimental.publishtraverse.egg-info/requires.txt
src/experimental.publishtraverse.egg-info/top_level.txt
src/experimental/publishtraverse/__init__.py
src/experimental/publishtraverse/configure.zcml
src/experimental/publishtraverse/testing.py
src/experimental/publishtraverse/traverser.py
src/experimental/publishtraverse/tests/__init__.py
src/experimental/publishtraverse/tests/test_publish_traverser.py
src/experimental/publishtraverse/tests/test_unit.py